aws_lambda_utils/__init__.py
aws_lambda_utils/cfnresponse.py
aws_lambda_utils-0.0.2.dist-info/DESCRIPTION.rst
aws_lambda_utils-0.0.2.dist-info/METADATA
aws_lambda_utils-0.0.2.dist-info/RECORD
aws_lambda_utils-0.0.2.dist-info/WHEEL
aws_lambda_utils-0.0.2.dist-info/metadata.json
aws_lambda_utils-0.0.2.dist-info/top_level.txt
